{"title":"Mr. Wrong","plot":"Martha is a single woman working at a television talk show. When her younger sister gets married, everyone's wondering when Martha is going to meet Mr. Right and tie the knot. When by chance, Martha meets a handsome stranger named Whitman, the two fall madly in love with each other. But soon Martha discovers little quirks in Whitman... little quirks that become horrifying nightmares. But by the time Martha realizes that she must break up with him, it'll take more than subtle hints to make him go away -- she'll have to get into the most outrageous predicaments to rid herself of Mr. Wrong.","genres":["Comedy"],"stems":["Martha","is","a","singl","woman","work","at","a","televis","talk","show",".","When","her","younger","sister","get","marri",",","everyon","'s","wonder","when","Martha","is","go","to","meet","Mr.","Right","and","tie","the","knot",".","When","by","chanc",",","Martha","meet","a","handsom","stranger","name","Whitman",",","the","two","fall","mad","in","love","with","each","other",".","But","soon","Martha","discov","littl","quirk","in","Whitman","...","littl","quirk","that","becom","horrifi","nightmar",".","But","by","the","time","Martha","realiz","that","she","must","break","up","with","him",",","it","ll","take","more","than","subtl","hint","to","make","him","go","away","--","she","ll","have","to","get","into","the","most","outrag","predica","to","rid","herself","of","Mr.","Wrong","."],"lemmas":["Martha","be","a","single","woman","work","at","a","television","talk","show",".","when","she","younger","sister","get","married",",","everyone","'s","wonder","when","Martha","be","go","to","meet","Mr.","Right","and","tie","the","knot",".","when","by","chance",",","Martha","meet","a","handsome","stranger","name","Whitman",",","the","two","fall","madly","in","love","with","each","other",".","but","soon","Martha","discover","little","quirk","in","Whitman","...","little","quirk","that","become","horrifying","nightmare",".","but","by","the","time","Martha","realize","that","she","must","break","up","with","he",",","it","will","take","more","than","subtle","hint","to","make","he","go","away","--","she","will","have","to","get","into","the","most","outrageous","predicament","to","rid","herself","of","Mr.","wrong","."],"named_entities":["PERSON","PERSON","PERSON","PERSON","PERSON","PERSON","PERSON","PERSON","PERSON"],"3grams":["Martha is a","is a single","a single woman","single woman working","woman working at","working at a","at a television","a television talk","television talk show","When her younger","her younger sister","younger sister gets","sister gets married","gets married ,","married , everyone",", everyone 's","everyone 's wondering","'s wondering when","wondering when Martha","when Martha is","Martha is going","is going to","going to meet","to meet Mr.","meet Mr. Right","Mr. Right and","Right and tie","and tie the","tie the knot","When by chance","by chance ,","chance , Martha",", Martha meets","Martha meets a","meets a handsome","a handsome stranger","handsome stranger named","stranger named Whitman","named Whitman ,","Whitman , the",", the two","the two fall","two fall madly","fall madly in","madly in love","in love with","love with each","with each other","But soon Martha","soon Martha discovers","Martha discovers little","discovers little quirks","little quirks in","quirks in Whitman","in Whitman ...","Whitman ... little","... little quirks","little quirks that","quirks that become","that become horrifying","become horrifying nightmares","But by the","by the time","the time Martha","time Martha realizes","Martha realizes that","realizes that she","that she must","she must break","must break up","break up with","up with him","with him ,","him , it",", it 'll","it 'll take","'ll take more","take more than","more than subtle","than subtle hints","subtle hints to","hints to make","to make him","make him go","him go away","go away --","away -- she","-- she 'll","she 'll have","'ll have to","have to get","to get into","get into the","into the most","the most outrageous","most outrageous predicaments","outrageous predicaments to","predicaments to rid","to rid herself","rid herself of","herself of Mr.","of Mr. Wrong"],"2grams":["Martha is","is a","a single","single woman","woman working","working at","at a","a television","television talk","talk show","When her","her younger","younger sister","sister gets","gets married","married ,",", everyone","everyone 's","'s wondering","wondering when","when Martha","Martha is","is going","going to","to meet","meet Mr.","Mr. Right","Right and","and tie","tie the","the knot","When by","by chance","chance ,",", Martha","Martha meets","meets a","a handsome","handsome stranger","stranger named","named Whitman","Whitman ,",", the","the two","two fall","fall madly","madly in","in love","love with","with each","each other","But soon","soon Martha","Martha discovers","discovers little","little quirks","quirks in","in Whitman","Whitman ...","... little","little quirks","quirks that","that become","become horrifying","horrifying nightmares","But by","by the","the time","time Martha","Martha realizes","realizes that","that she","she must","must break","break up","up with","with him","him ,",", it","it 'll","'ll take","take more","more than","than subtle","subtle hints","hints to","to make","make him","him go","go away","away --","-- she","she 'll","'ll have","have to","to get","get into","into the","the most","most outrageous","outrageous predicaments","predicaments to","to rid","rid herself","herself of","of Mr.","Mr. Wrong"]}