{"title":"Sex Positive","plot":"Sex Positive explores the life of Richard Berkowitz, a revolutionary gay S&M hustler turned AIDS activist in the 1980s, whose incomparable contribution to the invention of safe sex has never been aptly credited. Mr. Berkowitz emerged from the epicenter of the epidemic demanding a solution to the problem before the outside world would take heed. Now destitute and alone, Mr. Berkowitz tells his story to a world who never wanted to listen.","genres":["Documentary"],"stems":["Sex","Posit","explor","the","life","of","Richard","Berkowitz",",","a","revolutionari","gay","S&M","hustler","turn","AIDS","activist","in","the","1980s",",","whose","incompar","contribut","to","the","invent","of","safe","sex","has","never","been","apt","credit",".","Mr.","Berkowitz","emerg","from","the","epicent","of","the","epidem","demand","a","solut","to","the","problem","befor","the","outsid","world","would","take","heed",".","Now","destitut","and","alon",",","Mr.","Berkowitz","tell","his","stori","to","a","world","who","never","want","to","listen","."],"lemmas":["sex","positive","explore","the","life","of","Richard","Berkowitz",",","a","revolutionary","gay","s&m","hustler","turn","aids","activist","in","the","1980s",",","whose","incomparable","contribution","to","the","invention","of","safe","sex","have","never","be","aptly","credit",".","Mr.","Berkowitz","emerge","from","the","epicenter","of","the","epidemic","demand","a","solution","to","the","problem","before","the","outside","world","would","take","heed",".","now","destitute","and","alone",",","Mr.","Berkowitz","tell","he","story","to","a","world","who","never","want","to","listen","."],"named_entities":["PERSON","PERSON","PERSON"],"3grams":["Sex Positive explores","Positive explores the","explores the life","the life of","life of Richard","of Richard Berkowitz","Richard Berkowitz ,","Berkowitz , a",", a revolutionary","a revolutionary gay","revolutionary gay S&M","gay S&M hustler","S&M hustler turned","hustler turned AIDS","turned AIDS activist","AIDS activist in","activist in the","in the 1980s","the 1980s ,","1980s , whose",", whose incomparable","whose incomparable contribution","incomparable contribution to","contribution to the","to the invention","the invention of","invention of safe","of safe sex","safe sex has","sex has never","has never been","never been aptly","been aptly credited","Mr. Berkowitz emerged","Berkowitz emerged from","emerged from the","from the epicenter","the epicenter of","epicenter of the","of the epidemic","the epidemic demanding","epidemic demanding a","demanding a solution","a solution to","solution to the","to the problem","the problem before","problem before the","before the outside","the outside world","outside world would","world would take","would take heed","Now destitute and","destitute and alone","and alone ,","alone , Mr.",", Mr. Berkowitz","Mr. Berkowitz tells","Berkowitz tells his","tells his story","his story to","story to a","to a world","a world who","world who never","who never wanted","never wanted to","wanted to listen"],"2grams":["Sex Positive","Positive explores","explores the","the life","life of","of Richard","Richard Berkowitz","Berkowitz ,",", a","a revolutionary","revolutionary gay","gay S&M","S&M hustler","hustler turned","turned AIDS","AIDS activist","activist in","in the","the 1980s","1980s ,",", whose","whose incomparable","incomparable contribution","contribution to","to the","the invention","invention of","of safe","safe sex","sex has","has never","never been","been aptly","aptly credited","Mr. Berkowitz","Berkowitz emerged","emerged from","from the","the epicenter","epicenter of","of the","the epidemic","epidemic demanding","demanding a","a solution","solution to","to the","the problem","problem before","before the","the outside","outside world","world would","would take","take heed","Now destitute","destitute and","and alone","alone ,",", Mr.","Mr. Berkowitz","Berkowitz tells","tells his","his story","story to","to a","a world","world who","who never","never wanted","wanted to","to listen"]}