{"title":"Fling","plot":"Mindy always fall for the wrong guy. Japo is not ready for a relationship. Fiona is back to claim what is rightfully hers. Three hearts. Three different beats. Only one meaning, love.","genres":["Drama"," Romance"],"stems":["Mindi","alway","fall","for","the","wrong","guy",".","Japo","is","not","readi","for","a","relationship",".","Fiona","is","back","to","claim","what","is","right","her",".","Three","heart",".","Three","differ","beat",".","Onli","one","mean",",","love","."],"lemmas":["Mindy","always","fall","for","the","wrong","guy",".","Japo","be","not","ready","for","a","relationship",".","Fiona","be","back","to","claim","what","be","rightfully","hers",".","three","heart",".","three","different","beat",".","only","one","meaning",",","love","."],"named_entities":["PERSON","PERSON"],"3grams":["Mindy always fall","always fall for","fall for the","for the wrong","the wrong guy","Japo is not","is not ready","not ready for","ready for a","for a relationship","Fiona is back","is back to","back to claim","to claim what","claim what is","what is rightfully","is rightfully hers","Three different beats","Only one meaning","one meaning ,","meaning , love"],"2grams":["Mindy always","always fall","fall for","for the","the wrong","wrong guy","Japo is","is not","not ready","ready for","for a","a relationship","Fiona is","is back","back to","to claim","claim what","what is","is rightfully","rightfully hers","Three hearts","Three different","different beats","Only one","one meaning","meaning ,",", love"]}