{"title":"Redemption","plot":"Homeless and on the run from a military court martial, a damaged ex-special forces soldier navigating London's criminal underworld seizes an opportunity to assume another man's identity -- transforming into an avenging angel in the process.","genres":["Action"," Drama"," Crime"],"stems":["Homeless","and","on","the","run","from","a","militari","court","martial",",","a","damag","ex-speci","forc","soldier","navig","London","'s","crimin","underworld","seiz","an","opportun","to","assum","anoth","man","'s","ident","--","transform","into","an","aveng","angel","in","the","process","."],"lemmas":["homeless","and","on","the","run","from","a","military","court","martial",",","a","damage","ex-special","force","soldier","navigate","London","'s","criminal","underworld","seize","a","opportunity","to","assume","another","man","'s","identity","--","transform","into","a","avenge","angel","in","the","process","."],"named_entities":["LOCATION"],"3grams":["Homeless and on","and on the","on the run","the run from","run from a","from a military","a military court","military court martial","court martial ,","martial , a",", a damaged","a damaged ex-special","damaged ex-special forces","ex-special forces soldier","forces soldier navigating","soldier navigating London","navigating London 's","London 's criminal","'s criminal underworld","criminal underworld seizes","underworld seizes an","seizes an opportunity","an opportunity to","opportunity to assume","to assume another","assume another man","another man 's","man 's identity","'s identity --","identity -- transforming","-- transforming into","transforming into an","into an avenging","an avenging angel","avenging angel in","angel in the","in the process"],"2grams":["Homeless and","and on","on the","the run","run from","from a","a military","military court","court martial","martial ,",", a","a damaged","damaged ex-special","ex-special forces","forces soldier","soldier navigating","navigating London","London 's","'s criminal","criminal underworld","underworld seizes","seizes an","an opportunity","opportunity to","to assume","assume another","another man","man 's","'s identity","identity --","-- transforming","transforming into","into an","an avenging","avenging angel","angel in","in the","the process"]}