{"title":"Daemoniac","plot":"A heart transplant that was supposed to be life saving turns out to be life-threatening when a girl begins to suspect her donor may have been a victim of demonic possession. She sets out on a mission to try to discover the truth before it's too late.","genres":["Drama"," Horror"],"stems":["A","heart","transplant","that","was","suppos","to","be","life","save","turn","out","to","be","life-threaten","when","a","girl","begin","to","suspect","her","donor","may","have","been","a","victim","of","demon","possess",".","She","set","out","on","a","mission","to","tri","to","discov","the","truth","befor","it","'s","too","late","."],"lemmas":["a","heart","transplant","that","be","suppose","to","be","life","saving","turn","out","to","be","life-threatening","when","a","girl","begin","to","suspect","she","donor","may","have","be","a","victim","of","demonic","possession",".","she","set","out","on","a","mission","to","try","to","discover","the","truth","before","it","be","too","late","."],"named_entities":[],"3grams":["A heart transplant","heart transplant that","transplant that was","that was supposed","was supposed to","supposed to be","to be life","be life saving","life saving turns","saving turns out","turns out to","out to be","to be life-threatening","be life-threatening when","life-threatening when a","when a girl","a girl begins","girl begins to","begins to suspect","to suspect her","suspect her donor","her donor may","donor may have","may have been","have been a","been a victim","a victim of","victim of demonic","of demonic possession","She sets out","sets out on","out on a","on a mission","a mission to","mission to try","to try to","try to discover","to discover the","discover the truth","the truth before","truth before it","before it 's","it 's too","'s too late"],"2grams":["A heart","heart transplant","transplant that","that was","was supposed","supposed to","to be","be life","life saving","saving turns","turns out","out to","to be","be life-threatening","life-threatening when","when a","a girl","girl begins","begins to","to suspect","suspect her","her donor","donor may","may have","have been","been a","a victim","victim of","of demonic","demonic possession","She sets","sets out","out on","on a","a mission","mission to","to try","try to","to discover","discover the","the truth","truth before","before it","it 's","'s too","too late"]}