{"title":"The French Dip: A tale from Los Angeles","plot":"Two restaurants in Los Angeles claim to have originated one of the most famous deli sandwiches in the United States. Up until this day both restaurants hold on to the title originator of the French Dip. This short doc explores who is the originator of the French Dip. A short doc. (live action/animation) film on the French Dip, a Los Angeles original.","genres":["Biography"," Documentary"],"stems":["Two","restaur","in","Los","Angele","claim","to","have","origin","one","of","the","most","famous","deli","sandwich","in","the","Unite","State",".","Up","until","this","day","both","restaur","hold","on","to","the","titl","origin","of","the","French","Dip",".","This","short","doc","explor","who","is","the","origin","of","the","French","Dip",".","A","short","doc",".","(","live","action/anim",")","film","on","the","French","Dip",",","a","Los","Angele","origin","."],"lemmas":["two","restaurant","in","Los","Angeles","claim","to","have","originate","one","of","the","most","famous","deli","sandwich","in","the","United","States",".","up","until","this","day","both","restaurant","hold","on","to","the","title","originator","of","the","french","dip",".","this","short","doc","explore","who","be","the","originator","of","the","french","dip",".","a","short","doc",".","-lrb-","live","action/animation","-rrb-","film","on","the","french","dip",",","a","Los","Angeles","original","."],"named_entities":["LOCATION","LOCATION","LOCATION"],"3grams":["Two restaurants in","restaurants in Los","in Los Angeles","Los Angeles claim","Angeles claim to","claim to have","to have originated","have originated one","originated one of","one of the","of the most","the most famous","most famous deli","famous deli sandwiches","deli sandwiches in","sandwiches in the","in the United","the United States","Up until this","until this day","this day both","day both restaurants","both restaurants hold","restaurants hold on","hold on to","on to the","to the title","the title originator","title originator of","originator of the","of the French","the French Dip","This short doc","short doc explores","doc explores who","explores who is","who is the","is the originator","the originator of","originator of the","of the French","the French Dip","A short doc","( live action/animation","live action/animation )","action/animation ) film",") film on","film on the","on the French","the French Dip","French Dip ,","Dip , a",", a Los","a Los Angeles","Los Angeles original"],"2grams":["Two restaurants","restaurants in","in Los","Los Angeles","Angeles claim","claim to","to have","have originated","originated one","one of","of the","the most","most famous","famous deli","deli sandwiches","sandwiches in","in the","the United","United States","Up until","until this","this day","day both","both restaurants","restaurants hold","hold on","on to","to the","the title","title originator","originator of","of the","the French","French Dip","This short","short doc","doc explores","explores who","who is","is the","the originator","originator of","of the","the French","French Dip","A short","short doc","( live","live action/animation","action/animation )",") film","film on","on the","the French","French Dip","Dip ,",", a","a Los","Los Angeles","Angeles original"]}