{"title":"Remittance","plot":"When Marie takes a job as a maid in Singapore to support her family in the Philippines, she trades one set of hardships for another. Betrayed by her husband, she begins to build a new life for herself. As she gets caught up in the new life she is building for herself in Singapore, she needs to choose between her personal aspirations and her family responsibilities.","genres":["Drama"," Family"],"stems":["When","Mari","take","a","job","as","a","maid","in","Singapor","to","support","her","famili","in","the","Philippin",",","she","trade","one","set","of","hardship","for","anoth",".","Betray","by","her","husband",",","she","begin","to","build","a","new","life","for","herself",".","As","she","get","caught","up","in","the","new","life","she","is","build","for","herself","in","Singapor",",","she","need","to","choos","between","her","person","aspir","and","her","famili","respons","."],"lemmas":["when","Marie","take","a","job","as","a","maid","in","Singapore","to","support","she","family","in","the","Philippines",",","she","trade","one","set","of","hardship","for","another",".","betray","by","she","husband",",","she","begin","to","build","a","new","life","for","herself",".","as","she","get","catch","up","in","the","new","life","she","be","build","for","herself","in","Singapore",",","she","need","to","choose","between","she","personal","aspiration","and","she","family","responsibility","."],"named_entities":["PERSON","LOCATION","LOCATION","LOCATION"],"3grams":["When Marie takes","Marie takes a","takes a job","a job as","job as a","as a maid","a maid in","maid in Singapore","in Singapore to","Singapore to support","to support her","support her family","her family in","family in the","in the Philippines","the Philippines ,","Philippines , she",", she trades","she trades one","trades one set","one set of","set of hardships","of hardships for","hardships for another","Betrayed by her","by her husband","her husband ,","husband , she",", she begins","she begins to","begins to build","to build a","build a new","a new life","new life for","life for herself","As she gets","she gets caught","gets caught up","caught up in","up in the","in the new","the new life","new life she","life she is","she is building","is building for","building for herself","for herself in","herself in Singapore","in Singapore ,","Singapore , she",", she needs","she needs to","needs to choose","to choose between","choose between her","between her personal","her personal aspirations","personal aspirations and","aspirations and her","and her family","her family responsibilities"],"2grams":["When Marie","Marie takes","takes a","a job","job as","as a","a maid","maid in","in Singapore","Singapore to","to support","support her","her family","family in","in the","the Philippines","Philippines ,",", she","she trades","trades one","one set","set of","of hardships","hardships for","for another","Betrayed by","by her","her husband","husband ,",", she","she begins","begins to","to build","build a","a new","new life","life for","for herself","As she","she gets","gets caught","caught up","up in","in the","the new","new life","life she","she is","is building","building for","for herself","herself in","in Singapore","Singapore ,",", she","she needs","needs to","to choose","choose between","between her","her personal","personal aspirations","aspirations and","and her","her family","family responsibilities"]}