{"title":"Those Who Go Those Who Stay","plot":"Rain on a window pane, a fire truck, a tomcat with innumerable offspring: it is an intentionally unintentional gaze that allows for chance encounters, for stories and memories - leads that ...","genres":["Documentary"],"stems":["Rain","on","a","window","pane",",","a","fire","truck",",","a","tomcat","with","innumer","offspr",":","it","is","an","intent","unintent","gaze","that","allow","for","chanc","encount",",","for","stori","and","memori","-","lead","that","..."],"lemmas":["rain","on","a","window","pane",",","a","fire","truck",",","a","tomcat","with","innumerable","offspring",":","it","be","a","intentionally","unintentional","gaze","that","allow","for","chance","encounter",",","for","story","and","memory","-","lead","that","..."],"named_entities":[],"3grams":["Rain on a","on a window","a window pane","window pane ,","pane , a",", a fire","a fire truck","fire truck ,","truck , a",", a tomcat","a tomcat with","tomcat with innumerable","with innumerable offspring","innumerable offspring :","offspring : it",": it is","it is an","is an intentionally","an intentionally unintentional","intentionally unintentional gaze","unintentional gaze that","gaze that allows","that allows for","allows for chance","for chance encounters","chance encounters ,","encounters , for",", for stories","for stories and","stories and memories","and memories -","memories - leads","- leads that","leads that ..."],"2grams":["Rain on","on a","a window","window pane","pane ,",", a","a fire","fire truck","truck ,",", a","a tomcat","tomcat with","with innumerable","innumerable offspring","offspring :",": it","it is","is an","an intentionally","intentionally unintentional","unintentional gaze","gaze that","that allows","allows for","for chance","chance encounters","encounters ,",", for","for stories","stories and","and memories","memories -","- leads","leads that","that ..."]}