{"title":"Fluidø","plot":"Set in the post-AIDS future of 2060, where the Government is the first to declare the era AIDS FREE, mutated AIDS viruses give birth to ZERO GEN - humans that have genetically evolved in a very unique way. These gender fluid ZERO GENs are the bio-drug carriers whose white fluid is the hypernarcotic for the 21st century, taking over the markets of the 20th century white powder high. The ejaculate of these beings is intoxicating and the new form of sexual commodity in the future. The new drug, code named DELTA, diffuses through skin contact and creates an addictive high. A new war on drugs begins and the ZERO GEN are declared illegal. The Government dispatches drug-resistant replicants for round-up arrest missions. When one of these government android's immunity breaks down and its pleasure centers are activated, the story becomes a tangled multi-thread plot and the ZERO GENs are caught among underground drug lords, glitched super agents, a scheming corporation and a corrupt government. Check yourself in as a fluid junkie for a super hyper viral ride.","genres":["Sci-Fi"],"stems":["Set","in","the","post-AIDS","futur","of","2060",",","where","the","Govern","is","the","first","to","declar","the","era","AIDS","FREE",",","mutat","AIDS","virus","give","birth","to","ZERO","GEN","-","human","that","have","genet","evolv","in","a","veri","uniqu","way",".","These","gender","fluid","ZERO","GENs","are","the","bio-drug","carrier","whose","white","fluid","is","the","hypernarcot","for","the","21st","centuri",",","take","over","the","market","of","the","20th","centuri","white","powder","high",".","The","ejacul","of","these","be","is","intox","and","the","new","form","of","sexual","commod","in","the","futur",".","The","new","drug",",","code","name","DELTA",",","diffus","through","skin","contact","and","creat","an","addict","high",".","A","new","war","on","drug","begin","and","the","ZERO","GEN","are","declar","illeg",".","The","Govern","dispatch","drug-resist","replic","for","round-up","arrest","mission",".","When","one","of","these","govern","android","'s","immun","break","down","and","it","pleasur","center","are","activ",",","the","stori","becom","a","tangl","multi-thread","plot","and","the","ZERO","GENs","are","caught","among","underground","drug","lord",",","glitch","super","agent",",","a","scheme","corpor","and","a","corrupt","govern",".","Check","yourself","in","as","a","fluid","junki","for","a","super","hyper","viral","ride","."],"lemmas":["set","in","the","post-aids","future","of","2060",",","where","the","Government","be","the","first","to","declare","the","era","AIDS","FREE",",","mutate","aids","virus","give","birth","to","ZERO","GEN","-","human","that","have","genetically","evolve","in","a","very","unique","way",".","these","gender","fluid","ZERO","gen","be","the","bio-drug","carrier","whose","white","fluid","be","the","hypernarcotic","for","the","21st","century",",","take","over","the","market","of","the","20th","century","white","powder","high",".","the","ejaculate","of","these","being","be","intoxicate","and","the","new","form","of","sexual","commodity","in","the","future",".","the","new","drug",",","code","name","DELTA",",","diffuse","through","skin","contact","and","create","a","addictive","high",".","a","new","war","on","drug","begin","and","the","ZERO","GEN","be","declare","illegal",".","the","Government","dispatch","drug-resistant","replicant","for","round-up","arrest","mission",".","when","one","of","these","government","android","'s","immunity","break","down","and","its","pleasure","center","be","activate",",","the","story","become","a","tangled","multi-thread","plot","and","the","ZERO","gen","be","catch","among","underground","drug","lord",",","glitched","super","agent",",","a","scheming","corporation","and","a","corrupt","government",".","check","yourself","in","as","a","fluid","junkie","for","a","super","hyper","viral","ride","."],"named_entities":["ORGANIZATION"],"3grams":["Set in the","in the post-AIDS","the post-AIDS future","post-AIDS future of","future of 2060","of 2060 ,","2060 , where",", where the","where the Government","the Government is","Government is the","is the first","the first to","first to declare","to declare the","declare the era","the era AIDS","era AIDS FREE","AIDS FREE ,","FREE , mutated",", mutated AIDS","mutated AIDS viruses","AIDS viruses give","viruses give birth","give birth to","birth to ZERO","to ZERO GEN","ZERO GEN -","GEN - humans","- humans that","humans that have","that have genetically","have genetically evolved","genetically evolved in","evolved in a","in a very","a very unique","very unique way","These gender fluid","gender fluid ZERO","fluid ZERO GENs","ZERO GENs are","GENs are the","are the bio-drug","the bio-drug carriers","bio-drug carriers whose","carriers whose white","whose white fluid","white fluid is","fluid is the","is the hypernarcotic","the hypernarcotic for","hypernarcotic for the","for the 21st","the 21st century","21st century ,","century , taking",", taking over","taking over the","over the markets","the markets of","markets of the","of the 20th","the 20th century","20th century white","century white powder","white powder high","The ejaculate of","ejaculate of these","of these beings","these beings is","beings is intoxicating","is intoxicating and","intoxicating and the","and the new","the new form","new form of","form of sexual","of sexual commodity","sexual commodity in","commodity in the","in the future","The new drug","new drug ,","drug , code",", code named","code named DELTA","named DELTA ,","DELTA , diffuses",", diffuses through","diffuses through skin","through skin contact","skin contact and","contact and creates","and creates an","creates an addictive","an addictive high","A new war","new war on","war on drugs","on drugs begins","drugs begins and","begins and the","and the ZERO","the ZERO GEN","ZERO GEN are","GEN are declared","are declared illegal","The Government dispatches","Government dispatches drug-resistant","dispatches drug-resistant replicants","drug-resistant replicants for","replicants for round-up","for round-up arrest","round-up arrest missions","When one of","one of these","of these government","these government android","government android 's","android 's immunity","'s immunity breaks","immunity breaks down","breaks down and","down and its","and its pleasure","its pleasure centers","pleasure centers are","centers are activated","are activated ,","activated , the",", the story","the story becomes","story becomes a","becomes a tangled","a tangled multi-thread","tangled multi-thread plot","multi-thread plot and","plot and the","and the ZERO","the ZERO GENs","ZERO GENs are","GENs are caught","are caught among","caught among underground","among underground drug","underground drug lords","drug lords ,","lords , glitched",", glitched super","glitched super agents","super agents ,","agents , a",", a scheming","a scheming corporation","scheming corporation and","corporation and a","and a corrupt","a corrupt government","Check yourself in","yourself in as","in as a","as a fluid","a fluid junkie","fluid junkie for","junkie for a","for a super","a super hyper","super hyper viral","hyper viral ride"],"2grams":["Set in","in the","the post-AIDS","post-AIDS future","future of","of 2060","2060 ,",", where","where the","the Government","Government is","is the","the first","first to","to declare","declare the","the era","era AIDS","AIDS FREE","FREE ,",", mutated","mutated AIDS","AIDS viruses","viruses give","give birth","birth to","to ZERO","ZERO GEN","GEN -","- humans","humans that","that have","have genetically","genetically evolved","evolved in","in a","a very","very unique","unique way","These gender","gender fluid","fluid ZERO","ZERO GENs","GENs are","are the","the bio-drug","bio-drug carriers","carriers whose","whose white","white fluid","fluid is","is the","the hypernarcotic","hypernarcotic for","for the","the 21st","21st century","century ,",", taking","taking over","over the","the markets","markets of","of the","the 20th","20th century","century white","white powder","powder high","The ejaculate","ejaculate of","of these","these beings","beings is","is intoxicating","intoxicating and","and the","the new","new form","form of","of sexual","sexual commodity","commodity in","in the","the future","The new","new drug","drug ,",", code","code named","named DELTA","DELTA ,",", diffuses","diffuses through","through skin","skin contact","contact and","and creates","creates an","an addictive","addictive high","A new","new war","war on","on drugs","drugs begins","begins and","and the","the ZERO","ZERO GEN","GEN are","are declared","declared illegal","The Government","Government dispatches","dispatches drug-resistant","drug-resistant replicants","replicants for","for round-up","round-up arrest","arrest missions","When one","one of","of these","these government","government android","android 's","'s immunity","immunity breaks","breaks down","down and","and its","its pleasure","pleasure centers","centers are","are activated","activated ,",", the","the story","story becomes","becomes a","a tangled","tangled multi-thread","multi-thread plot","plot and","and the","the ZERO","ZERO GENs","GENs are","are caught","caught among","among underground","underground drug","drug lords","lords ,",", glitched","glitched super","super agents","agents ,",", a","a scheming","scheming corporation","corporation and","and a","a corrupt","corrupt government","Check yourself","yourself in","in as","as a","a fluid","fluid junkie","junkie for","for a","a super","super hyper","hyper viral","viral ride"]}