{"title":"Path Jodi Na Sesh Hoi","plot":"This movie is based on a love story. A girl named Titli meets with a car accident and she even loses her mother. Titli is severely injured on her head because of which she loses her memory ...","genres":["Action"," Romance"," Drama"],"stems":["This","movi","is","base","on","a","love","stori",".","A","girl","name","Tit","meet","with","a","car","accid","and","she","even","lose","her","mother",".","Tit","is","sever","injur","on","her","head","becaus","of","which","she","lose","her","memori","..."],"lemmas":["this","movie","be","base","on","a","love","story",".","a","girl","name","Titli","meet","with","a","car","accident","and","she","even","lose","she","mother",".","Titli","be","severely","injure","on","she","head","because","of","which","she","lose","she","memory","..."],"named_entities":["PERSON"],"3grams":["This movie is","movie is based","is based on","based on a","on a love","a love story","A girl named","girl named Titli","named Titli meets","Titli meets with","meets with a","with a car","a car accident","car accident and","accident and she","and she even","she even loses","even loses her","loses her mother","Titli is severely","is severely injured","severely injured on","injured on her","on her head","her head because","head because of","because of which","of which she","which she loses","she loses her","loses her memory","her memory ..."],"2grams":["This movie","movie is","is based","based on","on a","a love","love story","A girl","girl named","named Titli","Titli meets","meets with","with a","a car","car accident","accident and","and she","she even","even loses","loses her","her mother","Titli is","is severely","severely injured","injured on","on her","her head","head because","because of","of which","which she","she loses","loses her","her memory","memory ..."]}